LICENSE
MANIFEST.in
README.rst
setup.py
basic_cms/__init__.py
basic_cms/api.py
basic_cms/app_config.py
basic_cms/checks.py
basic_cms/context_processors.py
basic_cms/http.py
basic_cms/managers.py
basic_cms/models.py
basic_cms/permissions.py
basic_cms/placeholders.py
basic_cms/search_indexes.py
basic_cms/settings.py
basic_cms/test_runner.py
basic_cms/urlconf_registry.py
basic_cms/urls.py
basic_cms/utils.py
basic_cms/views.py
basic_cms/widgets.py
basic_cms/widgets_registry.py
basic_cms/admin/__init__.py
basic_cms/admin/actions.py
basic_cms/admin/forms.py
basic_cms/admin/utils.py
basic_cms/admin/views.py
basic_cms/fixtures/api.json
basic_cms/fixtures/pages_tests.json
basic_cms/locale/da/LC_MESSAGES/django.mo
basic_cms/locale/da/LC_MESSAGES/django.po
basic_cms/locale/de/LC_MESSAGES/django.mo
basic_cms/locale/de/LC_MESSAGES/django.po
basic_cms/locale/de/LC_MESSAGES/djangojs.mo
basic_cms/locale/de/LC_MESSAGES/djangojs.po
basic_cms/locale/es/LC_MESSAGES/django.mo
basic_cms/locale/es/LC_MESSAGES/django.po
basic_cms/locale/fr/LC_MESSAGES/django.mo
basic_cms/locale/fr/LC_MESSAGES/django.po
basic_cms/locale/he/LC_MESSAGES/django.mo
basic_cms/locale/he/LC_MESSAGES/django.po
basic_cms/locale/it/LC_MESSAGES/django.mo
basic_cms/locale/it/LC_MESSAGES/django.po
basic_cms/locale/nl/LC_MESSAGES/django.mo
basic_cms/locale/nl/LC_MESSAGES/django.po
basic_cms/locale/ru/LC_MESSAGES/django.mo
basic_cms/locale/ru/LC_MESSAGES/django.po
basic_cms/locale/ru/LC_MESSAGES/djangojs.mo
basic_cms/locale/ru/LC_MESSAGES/djangojs.po
basic_cms/locale/sk/LC_MESSAGES/django.mo
basic_cms/locale/sk/LC_MESSAGES/django.po
basic_cms/management/__init__.py
basic_cms/management/commands/__init__.py
basic_cms/management/commands/pages_export_po.py
basic_cms/management/commands/pages_import_po.py
basic_cms/migrations/0001_initial.py
basic_cms/migrations/0002_auto_20151221_0338.py
basic_cms/migrations/__init__.py
basic_cms/static/pages/ckeditor/CHANGES.html
basic_cms/static/pages/ckeditor/INSTALL.html
django_basic_cms.egg-info/PKG-INFO
django_basic_cms.egg-info/SOURCES.txt
django_basic_cms.egg-info/dependency_links.txt
django_basic_cms.egg-info/not-zip-safe
django_basic_cms.egg-info/requires.txt
django_basic_cms.egg-info/top_level.txt
